{"tripulantes":{"head":null,"size":0,"empty":true},"aeronaves":{"head":null,"size":0,"empty":true},"vuelosProgramados":{"head":null,"size":0,"empty":true},"clientes":{"head":{"data":{"identificacion":"246","contrasena":"246","nombre":"fev","apellido":"efbv","direccion":"efvb","correoElectronico":"246","fechaNacimiento":"2024-10-27","tickets":{"head":null,"size":0,"empty":true}},"next":null},"size":1,"empty":false},"rutas":{"head":null,"size":0,"empty":true},"estacionamiento":{"carrosEnBicola":[],"carrosEnEspera":[]}}